csmarketapi/__init__.py
csmarketapi/client.py
csmarketapi/enums.py
csmarketapi/models.py
csmarketapi-2.0.0.dist-info/licenses/LICENSE
csmarketapi-2.0.0.dist-info/METADATA
csmarketapi-2.0.0.dist-info/WHEEL
csmarketapi-2.0.0.dist-info/top_level.txt
csmarketapi-2.0.0.dist-info/RECORD
