Metadata-Version: 2.4
Name: csmarketapi
Version: 2.0.0
Summary: The official python library for CSMarketAPI
Author-email: Luis <luis@softwerk.ai>
Project-URL: Homepage, https://github.com/softwerk-org/csmarketapi-python
Project-URL: Issues, https://github.com/softwerk-org/csmarketapi-python/issues
Classifier: Programming Language :: Python :: 3
Classifier: Programming Language :: Python :: 3.10
Classifier: Programming Language :: Python :: 3.11
Classifier: Programming Language :: Python :: 3.12
Classifier: Operating System :: OS Independent
Requires-Python: >=3.10
License-File: LICENSE
Requires-Dist: httpx>=0.28.1
Requires-Dist: pydantic>=2.11.7
Provides-Extra: dev
Requires-Dist: black; extra == "dev"
Requires-Dist: ruff; extra == "dev"
Provides-Extra: test
Requires-Dist: dotenv>=0.9.9; extra == "test"
Requires-Dist: pytest; extra == "test"
Requires-Dist: pytest-asyncio; extra == "test"
Dynamic: license-file
